z3c.menu.ready2go-2.0-py3.9-nspkg.pth
z3c/menu/ready2go/README.txt
z3c/menu/ready2go/__init__.py
z3c/menu/ready2go/browser.zcml
z3c/menu/ready2go/checker.py
z3c/menu/ready2go/configure.zcml
z3c/menu/ready2go/i18n.py
z3c/menu/ready2go/interfaces.py
z3c/menu/ready2go/item.pt
z3c/menu/ready2go/item.py
z3c/menu/ready2go/manager.py
z3c/menu/ready2go/menu.pt
z3c/menu/ready2go/meta.zcml
z3c/menu/ready2go/testing.py
z3c/menu/ready2go/tests.py
z3c/menu/ready2go/zcml.py
z3c/menu/ready2go/zcml.txt
z3c.menu.ready2go-2.0.dist-info/LICENSE.txt
z3c.menu.ready2go-2.0.dist-info/METADATA
z3c.menu.ready2go-2.0.dist-info/WHEEL
z3c.menu.ready2go-2.0.dist-info/namespace_packages.txt
z3c.menu.ready2go-2.0.dist-info/top_level.txt
z3c.menu.ready2go-2.0.dist-info/RECORD
