Metadata-Version: 2.1
Name: z3c.menu.ready2go
Version: 2.0
Summary: A ready to go menu for Zope3
Home-page: https://github.com/zopefoundation/z3c.menu.ready2go
Author: Stephan Richter, Roger Ineichen and the Zope Community
Author-email: zope-dev@zope.dev
License: ZPL 2.1
Keywords: zope3 z3c ready 2 go menu
Classifier: Development Status :: 5 - Production/Stable
Classifier: Environment :: Web Environment
Classifier: Intended Audience :: Developers
Classifier: License :: OSI Approved :: Zope Public License
Classifier: Programming Language :: Python
Classifier: Programming Language :: Python :: 3
Classifier: Programming Language :: Python :: 3.7
Classifier: Programming Language :: Python :: 3.8
Classifier: Programming Language :: Python :: 3.9
Classifier: Programming Language :: Python :: 3.10
Classifier: Programming Language :: Python :: 3.11
Classifier: Programming Language :: Python :: Implementation :: CPython
Classifier: Programming Language :: Python :: Implementation :: PyPy
Classifier: Natural Language :: English
Classifier: Operating System :: OS Independent
Classifier: Topic :: Internet :: WWW/HTTP
Classifier: Framework :: Zope :: 3
Requires-Python: >=3.7
License-File: LICENSE.txt
Requires-Dist: setuptools
Requires-Dist: z3c.template
Requires-Dist: zope.browserpage
Requires-Dist: zope.component (>=3.8)
Requires-Dist: zope.configuration
Requires-Dist: zope.interface
Requires-Dist: zope.proxy
Requires-Dist: zope.publisher
Requires-Dist: zope.schema
Requires-Dist: zope.security
Requires-Dist: zope.site
Requires-Dist: zope.traversing
Requires-Dist: zope.viewlet
Provides-Extra: test
Requires-Dist: zope.browserpage ; extra == 'test'
Requires-Dist: zope.container ; extra == 'test'
Requires-Dist: zope.contentprovider ; extra == 'test'
Requires-Dist: zope.component ; extra == 'test'
Requires-Dist: zope.site ; extra == 'test'
Requires-Dist: zope.traversing ; extra == 'test'
Requires-Dist: zope.testing ; extra == 'test'
Requires-Dist: zope.testrunner ; extra == 'test'
